eth_logo/__init__.py
eth_logo/eth_logo_core.py
eth_logo/eth_logo_debug.py
eth_logo/eth_logo_script.py
eth_logo-0.1.3.data/scripts/eth_logo_script.py
eth_logo-0.1.3.dist-info/LICENSE
eth_logo-0.1.3.dist-info/METADATA
eth_logo-0.1.3.dist-info/WHEEL
eth_logo-0.1.3.dist-info/entry_points.txt
eth_logo-0.1.3.dist-info/top_level.txt
eth_logo-0.1.3.dist-info/RECORD
