Metadata-Version: 2.1
Name: eth-logo
Version: 0.1.3
Summary: Python lib to print Ethereum logo of any size and style on your terminal or standard output.
Home-page: https://github.com/0xMarto/eth-logo
Author: Marto
Author-email: martinlsanchez@gmail.com
Classifier: Programming Language :: Python :: 3
Classifier: License :: OSI Approved :: MIT License
Classifier: Operating System :: OS Independent
Requires-Python: >=3.6
License-File: LICENSE
